[
  {
    "dvnDisplayName": "Horizen (lzRead)",
    "dvnId": "horizen-labs",
    "originChainKey": "sonic",
    "originChainDisplayName": "Sonic Mainnet",
    "readLibAddressOnOriginChain": "0x860E8D714944E7accE4F9e6247923ec5d30c0471",
    "dvnAddressOnOriginChain": "0xca764b512e2d2fd15fca1c0a38f7cfe9153148f0",
    "dataChains": [
      {
        "dataChainKey": "abstract",
        "dataChainDisplayName": "Abstract Mainnet"
      },
      {
        "dataChainKey": "ape",
        "dataChainDisplayName": "Ape Mainnet"
      },
      {
        "dataChainKey": "arbitrum",
        "dataChainDisplayName": "Arbitrum Mainnet"
      },
      {
        "dataChainKey": "avalanche",
        "dataChainDisplayName": "Avalanche Mainnet"
      },
      {
        "dataChainKey": "base",
        "dataChainDisplayName": "Base Mainnet"
      },
      {
        "dataChainKey": "bera",
        "dataChainDisplayName": "Berachain Mainnet"
      },
      {
        "dataChainKey": "bsc",
        "dataChainDisplayName": "BNB Smart Chain (BSC) Mainnet"
      },
      {
        "dataChainKey": "celo",
        "dataChainDisplayName": "Celo Mainnet"
      },
      {
        "dataChainKey": "ethereum",
        "dataChainDisplayName": "Ethereum Mainnet"
      },
      {
        "dataChainKey": "etherlink",
        "dataChainDisplayName": "Etherlink Mainnet"
      },
      {
        "dataChainKey": "hyperliquid",
        "dataChainDisplayName": "HyperEVM Mainnet"
      },
      {
        "dataChainKey": "ink",
        "dataChainDisplayName": "Ink Mainnet"
      },
      {
        "dataChainKey": "mantle",
        "dataChainDisplayName": "Mantle Mainnet"
      },
      {
        "dataChainKey": "mode",
        "dataChainDisplayName": "Mode Mainnet"
      },
      {
        "dataChainKey": "optimism",
        "dataChainDisplayName": "Optimism Mainnet"
      },
      {
        "dataChainKey": "polygon",
        "dataChainDisplayName": "Polygon Mainnet"
      },
      {
        "dataChainKey": "scroll",
        "dataChainDisplayName": "Scroll Mainnet"
      },
      {
        "dataChainKey": "sei",
        "dataChainDisplayName": "Sei Mainnet"
      },
      {
        "dataChainKey": "soneium",
        "dataChainDisplayName": "Soneium Mainnet"
      },
      {
        "dataChainKey": "sonic",
        "dataChainDisplayName": "Sonic Mainnet"
      },
      {
        "dataChainKey": "story",
        "dataChainDisplayName": "Story Mainnet"
      },
      {
        "dataChainKey": "unichain",
        "dataChainDisplayName": "Unichain Mainnet"
      },
      {
        "dataChainKey": "worldchain",
        "dataChainDisplayName": "Worldchain Mainnet"
      }
    ]
  },
  {
    "dvnDisplayName": "LayerZero Labs (lzRead)",
    "dvnId": "layerzero-labs",
    "originChainKey": "sonic",
    "originChainDisplayName": "Sonic Mainnet",
    "readLibAddressOnOriginChain": "0x860E8D714944E7accE4F9e6247923ec5d30c0471",
    "dvnAddressOnOriginChain": "0x78f607fc38e071ceb8630b7b12c358ee01c31e96",
    "dataChains": [
      {
        "dataChainKey": "abstract",
        "dataChainDisplayName": "Abstract Mainnet"
      },
      {
        "dataChainKey": "ape",
        "dataChainDisplayName": "Ape Mainnet"
      },
      {
        "dataChainKey": "arbitrum",
        "dataChainDisplayName": "Arbitrum Mainnet"
      },
      {
        "dataChainKey": "avalanche",
        "dataChainDisplayName": "Avalanche Mainnet"
      },
      {
        "dataChainKey": "base",
        "dataChainDisplayName": "Base Mainnet"
      },
      {
        "dataChainKey": "bera",
        "dataChainDisplayName": "Berachain Mainnet"
      },
      {
        "dataChainKey": "bsc",
        "dataChainDisplayName": "BNB Smart Chain (BSC) Mainnet"
      },
      {
        "dataChainKey": "celo",
        "dataChainDisplayName": "Celo Mainnet"
      },
      {
        "dataChainKey": "ethereum",
        "dataChainDisplayName": "Ethereum Mainnet"
      },
      {
        "dataChainKey": "etherlink",
        "dataChainDisplayName": "Etherlink Mainnet"
      },
      {
        "dataChainKey": "hyperliquid",
        "dataChainDisplayName": "HyperEVM Mainnet"
      },
      {
        "dataChainKey": "ink",
        "dataChainDisplayName": "Ink Mainnet"
      },
      {
        "dataChainKey": "mantle",
        "dataChainDisplayName": "Mantle Mainnet"
      },
      {
        "dataChainKey": "mode",
        "dataChainDisplayName": "Mode Mainnet"
      },
      {
        "dataChainKey": "optimism",
        "dataChainDisplayName": "Optimism Mainnet"
      },
      {
        "dataChainKey": "plumephoenix",
        "dataChainDisplayName": "Plume Mainnet"
      },
      {
        "dataChainKey": "polygon",
        "dataChainDisplayName": "Polygon Mainnet"
      },
      {
        "dataChainKey": "scroll",
        "dataChainDisplayName": "Scroll Mainnet"
      },
      {
        "dataChainKey": "sei",
        "dataChainDisplayName": "Sei Mainnet"
      },
      {
        "dataChainKey": "soneium",
        "dataChainDisplayName": "Soneium Mainnet"
      },
      {
        "dataChainKey": "sonic",
        "dataChainDisplayName": "Sonic Mainnet"
      },
      {
        "dataChainKey": "story",
        "dataChainDisplayName": "Story Mainnet"
      },
      {
        "dataChainKey": "unichain",
        "dataChainDisplayName": "Unichain Mainnet"
      },
      {
        "dataChainKey": "worldchain",
        "dataChainDisplayName": "Worldchain Mainnet"
      }
    ]
  },
  {
    "dvnDisplayName": "Nethermind (lzRead)",
    "dvnId": "nethermind",
    "originChainKey": "sonic",
    "originChainDisplayName": "Sonic Mainnet",
    "readLibAddressOnOriginChain": "0x860E8D714944E7accE4F9e6247923ec5d30c0471",
    "dvnAddressOnOriginChain": "0x3b0531eb02ab4ad72e7a531180beef9493a00dd2",
    "dataChains": [
      {
        "dataChainKey": "abstract",
        "dataChainDisplayName": "Abstract Mainnet"
      },
      {
        "dataChainKey": "arbitrum",
        "dataChainDisplayName": "Arbitrum Mainnet"
      },
      {
        "dataChainKey": "avalanche",
        "dataChainDisplayName": "Avalanche Mainnet"
      },
      {
        "dataChainKey": "base",
        "dataChainDisplayName": "Base Mainnet"
      },
      {
        "dataChainKey": "bera",
        "dataChainDisplayName": "Berachain Mainnet"
      },
      {
        "dataChainKey": "bsc",
        "dataChainDisplayName": "BNB Smart Chain (BSC) Mainnet"
      },
      {
        "dataChainKey": "celo",
        "dataChainDisplayName": "Celo Mainnet"
      },
      {
        "dataChainKey": "ethereum",
        "dataChainDisplayName": "Ethereum Mainnet"
      },
      {
        "dataChainKey": "etherlink",
        "dataChainDisplayName": "Etherlink Mainnet"
      },
      {
        "dataChainKey": "hyperliquid",
        "dataChainDisplayName": "HyperEVM Mainnet"
      },
      {
        "dataChainKey": "ink",
        "dataChainDisplayName": "Ink Mainnet"
      },
      {
        "dataChainKey": "mantle",
        "dataChainDisplayName": "Mantle Mainnet"
      },
      {
        "dataChainKey": "mode",
        "dataChainDisplayName": "Mode Mainnet"
      },
      {
        "dataChainKey": "optimism",
        "dataChainDisplayName": "Optimism Mainnet"
      },
      {
        "dataChainKey": "plumephoenix",
        "dataChainDisplayName": "Plume Mainnet"
      },
      {
        "dataChainKey": "polygon",
        "dataChainDisplayName": "Polygon Mainnet"
      },
      {
        "dataChainKey": "scroll",
        "dataChainDisplayName": "Scroll Mainnet"
      },
      {
        "dataChainKey": "sei",
        "dataChainDisplayName": "Sei Mainnet"
      },
      {
        "dataChainKey": "soneium",
        "dataChainDisplayName": "Soneium Mainnet"
      },
      {
        "dataChainKey": "sonic",
        "dataChainDisplayName": "Sonic Mainnet"
      },
      {
        "dataChainKey": "story",
        "dataChainDisplayName": "Story Mainnet"
      },
      {
        "dataChainKey": "unichain",
        "dataChainDisplayName": "Unichain Mainnet"
      },
      {
        "dataChainKey": "worldchain",
        "dataChainDisplayName": "Worldchain Mainnet"
      }
    ]
  }
]