{
  "deployment_info": {
    "name": "OmniDragon Multi-Chain Deployment",
    "version": "1.0.0",
    "deployment_type": "CREATE2",
    "deployment_date": "2024-12-19",
    "status": "ACTIVE"
  },
  "shared_configuration": {
    "owner": "0xDDd0050d1E084dFc72d5d06447Cc10bcD3fEF60F",
    "factory": "0xAA28020DDA6b954D16208eccF873D79AC6533833",
    "solidity_version": "0.8.20",
    "vanity_pattern": "0x69...0777"
  },
  "deployments": {
    "registry": {
      "contract_name": "OmniDragonRegistry",
      "networks": {
        "hype": {
          "address": "0x6940aDc0A505108bC11CA28EefB7E3BAc7AF0777",
          "chain_id": null,
          "status": "DEPLOYED"
        },
        "sonic": {
          "address": "0x6940aDc0A505108bC11CA28EefB7E3BAc7AF0777",
          "chain_id": 146,
          "status": "DEPLOYED"
        },
        "arbitrum": {
          "address": "0x6940aDc0A505108bC11CA28EefB7E3BAc7AF0777",
          "chain_id": 42161,
          "status": "DEPLOYED"
        },
        "ethereum": {
          "address": "0x6940aDc0A505108bC11CA28EefB7E3BAc7AF0777",
          "chain_id": 1,
          "status": "DEPLOYED"
        },
        "tac": {
          "address": "0x6940aDc0A505108bC11CA28EefB7E3BAc7AF0777",
          "chain_id": null,
          "status": "DEPLOYED"
        },
        "base": {
          "address": "0x6940aDc0A505108bC11CA28EefB7E3BAc7AF0777",
          "chain_id": 8453,
          "status": "DEPLOYED"
        },
        "unichain": {
          "address": "0x6940aDc0A505108bC11CA28EefB7E3BAc7AF0777",
          "chain_id": null,
          "status": "DEPLOYED"
        },
        "avalanche": {
          "address": "0x6940aDc0A505108bC11CA28EefB7E3BAc7AF0777",
          "chain_id": 43114,
          "status": "DEPLOYED"
        }
      }
    }
  }
}
